annlab/__init__.py
annlab/module1.py
annlab/module10.py
annlab/module2.py
annlab/module3.py
annlab/module4.py
annlab/module5.py
annlab/module6.py
annlab/module7.py
annlab/module8.py
annlab/module9.py
annlab-0.1.0.dist-info/METADATA
annlab-0.1.0.dist-info/WHEEL
annlab-0.1.0.dist-info/top_level.txt
annlab-0.1.0.dist-info/RECORD
