Metadata-Version: 2.1
Name: annlab
Version: 0.1.0
Summary: ANN Lab
Author: Anonymous
Author-email: niharrdg@gmail.com
